[{"id":"5a2qo7i4ksc0u8ds","contacts":[{"type":"phone","value":"815-519-5698"},{"type":"email","value":"Tate60@gmail.com"},{"type":"twitter","value":"Isabel.Swift"},{"type":"skype","value":"Lenora_Carroll"},{"type":"discord","value":"Niko.Jenkins44"}],"name":{"first":"Chasity","last":"Jones"},"avatar":"http://localhost:5000/5a2qo7i4ksc0u8ds.png","location":"Montserrat","createdAt":"2021-08-14T16:56:31.984Z","updatedAt":"2021-08-14T20:10:06.721Z"},{"contacts":[{"type":"phone","value":"995-635-5527"},{"type":"email","value":"Rick_Harber@hotmail.com"},{"type":"twitter","value":"Roselyn_Medhurst26"},{"type":"skype","value":"Jed53"},{"type":"discord","value":"Lucious.McLaughlin"}],"name":{"first":"Simeon","last":"Johnson"},"avatar":"http://placeimg.com/640/480","location":"Myanmar","id":"5a2qo7i4ksc0ucn9","createdAt":"2021-08-14T16:56:37.509Z"},{"contacts":[{"type":"phone","value":"834-947-9565"},{"type":"email","value":"Rafael.Hilpert@gmail.com"},{"type":"twitter","value":"Meggie.Morar38"},{"type":"skype","value":"Trey_Ritchie92"},{"type":"discord","value":"Rachel_Reichert17"}],"name":{"first":"Leta","last":"Kiehn"},"avatar":"http://placeimg.com/640/480","location":"Samoa","id":"5a2qo7i4ksc0udhf","createdAt":"2021-08-14T16:56:38.595Z"}]
